battleofai/__init__.py
battleofai/abc.py
battleofai/ais.py
battleofai/client.py
battleofai/config.py
battleofai/enums.py
battleofai/game.py
battleofai/game_types.py
battleofai/utils.py
battleofai-0.1.1.dist-info/METADATA
battleofai-0.1.1.dist-info/RECORD
battleofai-0.1.1.dist-info/WHEEL
battleofai-0.1.1.dist-info/top_level.txt
