Metadata-Version: 2.1
Name: battleofai
Version: 0.1.1
Summary: A wrapper for the battleofai API.
Home-page: https://github.com/LiBa001/python-battleofai
Author: Linus Bartsch
Author-email: linus.pypi@mabasoft.de
License: MIT
Project-URL: API, https://games.battleofai.net/api/
Project-URL: Related project, https://github.com/TheMorpheus407/BattleOfAI
Keywords: wrapper library API AI python
Platform: UNKNOWN
Classifier: License :: OSI Approved :: MIT License
Classifier: Programming Language :: Python :: 3.6
Requires-Python: >=3.6
Requires-Dist: requests
